AUTHORS.rst
CONTRIBUTING.rst
HISTORY.rst
LICENSE
MANIFEST.in
README.rst
setup.cfg
setup.py
docs/Makefile
docs/authors.rst
docs/conf.py
docs/contributing.rst
docs/history.rst
docs/index.rst
docs/installation.rst
docs/make.bat
docs/readme.rst
docs/usage.rst
pymcq/__init__.py
pymcq/mcqgrade.py
pymcq/mcqjson.py
pymcq/mcqtex.py
pymcq/mcqtypes.py
pymcq.egg-info/PKG-INFO
pymcq.egg-info/SOURCES.txt
pymcq.egg-info/dependency_links.txt
pymcq.egg-info/not-zip-safe
pymcq.egg-info/top_level.txt
pymcq/examples/__init__.py
pymcq/examples/heavymath/__init__.py
pymcq/examples/heavymath/test.py
pymcq/examples/heavymath/testsuite1/__init__.py
pymcq/examples/heavymath/testsuite1/question1.py
pymcq/examples/heavymath/testsuite1/question2.py
tests/__init__.py
tests/testimport.py