Metadata-Version: 1.1
Name: pymcq
Version: 0.1.6
Summary: This is a project that integrates latex exam into pyhon for easier creating of mcq tests.
Home-page: https://github.com/sglumac/pymcq
Author: Slaven Glumac
Author-email: slaven.glumac@gmail.com
License: MIT
Keywords: pymcq
Platform: UNKNOWN
Classifier: Development Status :: 2 - Pre-Alpha
Classifier: Intended Audience :: Developers
Classifier: License :: OSI Approved :: MIT License
Classifier: Natural Language :: English
Classifier: Programming Language :: Python :: 2.7
